[
    {
        "_id":1,
        "name":"Karyen Anderson",
        "postion":"BTP -  Senior Physiotherapist",
        "star":5,
        "address":"Dhanmondi, Dhaka, Bangladesh",
        // "image":"",
        "dates":"Available On Mon, 22 December",
        "price": 15
    },
    {
        "_id":1,
        "name":"Karyen Anderson",
        "postion":"BTP -  Senior Physiotherapist",
        "star":5,
        "address":"Dhanmondi, Dhaka, Bangladesh",
        "dates":"Available On Mon, 22 December",
        "price": 15
    },
    {
        "_id":1,
        "name":"Karyen Anderson",
        "postion":"BTP -  Senior Physiotherapist",
        "star":5,
        "address":"Dhanmondi, Dhaka, Bangladesh",
        "dates":"Available On Mon, 22 December",
        "price": 15
    }
]